LICENSE
MANIFEST.in
README.rst
setup.py
carfinder/__init__.py
carfinder/asgi.py
carfinder/settings.py
carfinder/urls.py
carfinder/wsgi.py
django_finder.egg-info/PKG-INFO
django_finder.egg-info/SOURCES.txt
django_finder.egg-info/dependency_links.txt
django_finder.egg-info/top_level.txt
finder/__init__.py
finder/admin.py
finder/apps.py
finder/forms.py
finder/models.py
finder/tests.py
finder/views.py
finder/migrations/__init__.py
finder/static/css/style.css
finder/static/media/2012-mercedes-benz-e350-fd.jpg
finder/static/media/2019-bmw-3-series.jpg
finder/static/media/plot.png
finder/static/media/plot_PzyBlIP.png
finder/templates/index.html
finder/templates/result.html
finder/templates/upload.html