Metadata-Version: 1.1
Name: django-finder
Version: 0.0.1
Summary: A Django app to find car make/model/year from photo.
Home-page: https://github.com/GaboxFH/cis4930-carfinder
Author: Gabriel Fernandez, Bao Nguyem, Kyle Bradley, Ziyad Morsi, Eric Gorday
Author-email: kyle.bradley@ufl.edu
License: UF License
Platform: UNKNOWN
Classifier: Environment :: Web Environment
Classifier: Framework :: Django
Classifier: Framework :: Django :: 3.0
Classifier: Intended Audience :: Developers
Classifier: License :: OSI Approved :: BSD License
Classifier: Operating System :: OS Independent
Classifier: Programming Language :: Python
Classifier: Programming Language :: Python :: 3
Classifier: Programming Language :: Python :: 3 :: Only
Classifier: Programming Language :: Python :: 3.6
Classifier: Programming Language :: Python :: 3.7
Classifier: Programming Language :: Python :: 3.8
Classifier: Topic :: Internet :: WWW/HTTP
Classifier: Topic :: Internet :: WWW/HTTP :: Dynamic Content
